centralmind/__init__.py
centralmind/core.py
centralmind-0.1.0.dist-info/LICENSE
centralmind-0.1.0.dist-info/METADATA
centralmind-0.1.0.dist-info/WHEEL
centralmind-0.1.0.dist-info/top_level.txt
centralmind-0.1.0.dist-info/RECORD
