Metadata-Version: 2.1
Name: centralmind
Version: 0.1.0
Summary: The official Python library for the CentralMind API
Author-email: CentralMind <contact@centralmind.ai>
License: MIT License
Requires-Python: >=3.7
License-File: LICENSE
